[
  {
    "Event": "ATP. Bastad",
    "matches": [
      {
        "game1": [
          {
            "name": "Rafael Nadal"
          },
          {
            "name": "Duje Ajdukovic"
          }
        ],
        "rates": [
          "1.33",
          "-",
          "3.38",
          "1.89",
          "21.5",
          "1.89",
          "1.71",
          "-3.5+",
          "2.1"
        ]
      },
      {
        "game2": [
          {
            "name": "Thiago Agustin Tirante"
          },
          {
            "name": "Nuno Borges"
          }
        ],
        "rates": [
          "2.426",
          "-",
          "1.57",
          "1.87",
          "22.5",
          "1.909",
          "1.835",
          "+2.5-",
          "1.825"
        ]
      }
    ],
    "head": [
      "1",
      "X",
      "2",
      "O",
      "TOTAL",
      "U",
      "1",
      "HANDICAP",
      "2"
    ]
  },
  {
    "Event": "ATP. Hamburg",
    "matches": [
      {
        "game1": [
          {
            "name": "Sebastian Baez"
          },
          {
            "name": "Arthur Fils"
          }
        ],
        "rates": [
          "2.159",
          "-",
          "1.71",
          "1.92",
          "22.5",
          "1.86",
          "1.865",
          "+1.5-",
          "1.797"
        ]
      },
      {
        "game2": [
          {
            "name": "Alexander Zverev"
          },
          {
            "name": "Pedro Martinez Portero"
          }
        ],
        "rates": [
          "1.099",
          "-",
          "7.3",
          "1.9",
          "20.5",
          "1.88",
          "2.056",
          "-5.5+",
          "1.649"
        ]
      }
    ],
    "head": [
      "1",
      "X",
      "2",
      "O",
      "TOTAL",
      "U",
      "1",
      "HANDICAP",
      "2"
    ]
  },
  {
    "Event": "ATP. Gstaad",
    "matches": [
      {
        "game1": [
          {
            "name": "Stefanos Tsitsipas"
          },
          {
            "name": "Matteo Berrettini"
          }
        ],
        "rates": [
          "1.68",
          "-",
          "2.217",
          "1.95",
          "25.5",
          "1.833",
          "1.825",
          "-1.5+",
          "1.835"
        ]
      }
    ],
    "head": [
      "1",
      "X",
      "2",
      "O",
      "TOTAL",
      "U",
      "1",
      "HANDICAP",
      "2"
    ]
  },
  {
    "Event": "ATP. Newport",
    "matches": [
      {
        "game1": [
          {
            "name": "Reilly Opelka"
          },
          {
            "name": "Alex Michelsen"
          }
        ],
        "rates": [
          "2.169",
          "-",
          "1.7",
          "1.83",
          "24.5",
          "1.95",
          "1.815",
          "+1.5-",
          "1.845"
        ]
      },
      {
        "game2": [
          {
            "name": "Christopher Eubanks"
          },
          {
            "name": "Marcos Giron"
          }
        ],
        "rates": [
          "2.454",
          "-",
          "1.56",
          "1.96",
          "23.5",
          "1.82",
          "1.768",
          "+2.5-",
          "1.896"
        ]
      }
    ],
    "head": [
      "1",
      "X",
      "2",
      "O",
      "TOTAL",
      "U",
      "1",
      "HANDICAP",
      "2"
    ]
  },
  {
    "Event": "WTA. Budapest",
    "matches": [
      {
        "game1": [
          {
            "name": "Anna Karolína Schmiedlova"
          },
          {
            "name": "Aliaksandra Sasnovich"
          }
        ],
        "rates": [
          "1.74",
          "-",
          "2.1",
          "1.86",
          "21.5",
          "1.92",
          "1.83",
          "-1.5+",
          "1.83"
        ]
      },
      {
        "game2": [
          {
            "name": "Diana Shnaider"
          },
          {
            "name": "Eva Lys"
          }
        ],
        "rates": [
          "1.37",
          "-",
          "3.13",
          "1.95",
          "20.5",
          "1.83",
          "1.909",
          "-4.5+",
          "1.86"
        ]
      }
    ],
    "head": [
      "1",
      "X",
      "2",
      "O",
      "TOTAL",
      "U",
      "1",
      "HANDICAP",
      "2"
    ]
  },
  {
    "Event": "WTA. Palermo",
    "matches": [
      {
        "game1": [
          {
            "name": "Qinwen Zheng"
          },
          {
            "name": "Diane Parry"
          }
        ],
        "rates": [
          "1.27",
          "-",
          "3.845",
          "1.87",
          "20.5",
          "1.909",
          "1.83",
          "-4.5+",
          "1.94"
        ]
      },
      {
        "game2": [
          {
            "name": "Irina-Camelia Begu"
          },
          {
            "name": "Karolina Muchova"
          }
        ],
        "rates": [
          "1.84",
          "-",
          "1.97",
          "1.85",
          "21.5",
          "1.93",
          "1.825",
          "-0.5+",
          "1.835"
        ]
      }
    ],
    "head": [
      "1",
      "X",
      "2",
      "O",
      "TOTAL",
      "U",
      "1",
      "HANDICAP",
      "2"
    ]
  },
  {
    "Event": "Challenger. Astana. Doubles",
    "matches": [
      {
        "game1": [
          {
            "name": "Istomin/Karlovskiy"
          },
          {
            "name": "Agafonov/Simakin"
          }
        ],
        "rates": [
          "1.72",
          "-",
          "2.02",
          "-",
          "-",
          "-",
          "-",
          "-",
          "-"
        ]
      }
    ],
    "head": [
      "1",
      "X",
      "2",
      "O",
      "TOTAL",
      "U",
      "1",
      "HANDICAP",
      "2"
    ]
  },
  {
    "Event": "ITF. Bucharest. Doubles",
    "matches": [
      {
        "game1": [
          {
            "name": "Denolly/Pavel"
          },
          {
            "name": "Andreescu/Cazacu"
          }
        ],
        "rates": [
          "1.141",
          "-",
          "5.13",
          "-",
          "-",
          "-",
          "-",
          "-",
          "-"
        ]
      }
    ],
    "head": [
      "1",
      "X",
      "2",
      "O",
      "TOTAL",
      "U",
      "1",
      "HANDICAP",
      "2"
    ]
  },
  {
    "Event": "ITF. Casablanca. Women",
    "matches": [
      {
        "game1": [
          {
            "name": "Tina Nadine Smith"
          },
          {
            "name": "Ekaterina Kazionova"
          }
        ],
        "rates": [
          "1.31",
          "-",
          "3.235",
          "1.94",
          "20.5",
          "1.77",
          "1.81",
          "-4.5+",
          "1.9"
        ]
      },
      {
        "game2": [
          {
            "name": "Paula Arias Manjon"
          },
          {
            "name": "Joelle Lilly Sophie Steur"
          }
        ],
        "rates": [
          "2.724",
          "-",
          "1.42",
          "1.87",
          "20.5",
          "1.84",
          "1.98",
          "+3.5-",
          "1.74"
        ]
      }
    ],
    "head": [
      "1",
      "X",
      "2",
      "O",
      "TOTAL",
      "U",
      "1",
      "HANDICAP",
      "2"
    ]
  },
  {
    "Event": "UTR Pro Tennis Series. Olomouc. Women",
    "matches": [
      {
        "game1": [
          {
            "name": "Nikola Breckova"
          },
          {
            "name": "Christina Zamechnikova"
          }
        ],
        "rates": [
          "1.04",
          "-",
          "9.4",
          "-",
          "-",
          "-",
          "-",
          "-",
          "-"
        ]
      },
      {
        "game2": [
          {
            "name": "Adela Latalova"
          },
          {
            "name": "Simona Wirglerova"
          }
        ],
        "rates": [
          "2.498",
          "-",
          "1.51",
          "-",
          "-",
          "-",
          "-",
          "-",
          "-"
        ]
      },
      {
        "game3": [
          {
            "name": "Petra Sedlackova"
          },
          {
            "name": "Aneta Laboutkova"
          }
        ],
        "rates": [
          "2.24",
          "-",
          "1.591",
          "-",
          "-",
          "-",
          "-",
          "-",
          "-"
        ]
      }
    ],
    "head": [
      "1",
      "X",
      "2",
      "O",
      "TOTAL",
      "U",
      "1",
      "HANDICAP",
      "2"
    ]
  },
  {
    "Event": "ATP. Kitzbühel. Qualification",
    "matches": [
      {
        "game1": [
          {
            "name": "Albert Ramos"
          },
          {
            "name": "Sandro Kopp"
          }
        ],
        "rates": [
          "1.42",
          "-",
          "2.758",
          "1.77",
          "21.5",
          "1.96",
          "1.89",
          "-3.5+",
          "1.83"
        ]
      },
      {
        "game2": [
          {
            "name": "Alexander Weis"
          },
          {
            "name": "Otto Virtanen"
          }
        ],
        "rates": [
          "2.64",
          "-",
          "1.454",
          "1.93",
          "22.5",
          "1.79",
          "1.727",
          "+3.5-",
          "2.02"
        ]
      },
      {
        "game3": [
          {
            "name": "Vit Kopriva"
          },
          {
            "name": "Ignacio Buse"
          }
        ],
        "rates": [
          "1.98",
          "-",
          "1.77",
          "1.98",
          "22.5",
          "1.75",
          "1.87",
          "+0.5-",
          "1.791"
        ]
      },
      {
        "game4": [
          {
            "name": "Daniel Elahi Galan Riveros"
          },
          {
            "name": "Pierre-Hugues Herbert"
          }
        ],
        "rates": [
          "1.57",
          "-",
          "2.33",
          "1.78",
          "22.5",
          "1.95",
          "1.92",
          "-2.5+",
          "1.81"
        ]
      },
      {
        "game5": [
          {
            "name": "Hamad Medjedovic"
          },
          {
            "name": "Alexander Erler"
          }
        ],
        "rates": [
          "1.015",
          "-",
          "12.5",
          "1.89",
          "18.5",
          "1.83",
          "2.01",
          "-6.5+",
          "1.73"
        ]
      }
    ],
    "head": [
      "1",
      "X",
      "2",
      "O",
      "TOTAL",
      "U",
      "1",
      "HANDICAP",
      "2"
    ]
  },
  {
    "Event": "ITF. Castelo Branco",
    "matches": [
      {
        "game1": [
          {
            "name": "Goncalo Oliveira"
          },
          {
            "name": "Frederico Ferreira Silva"
          }
        ],
        "rates": [
          "2.102",
          "-",
          "1.68",
          "1.93",
          "22.5",
          "1.78",
          "1.88",
          "+1.5-",
          "1.83"
        ]
      }
    ],
    "head": [
      "1",
      "X",
      "2",
      "O",
      "TOTAL",
      "U",
      "1",
      "HANDICAP",
      "2"
    ]
  },
  {
    "Event": "ITF. Kursumlijska Banja. Women. Doubles",
    "matches": [
      {
        "game1": [
          {
            "name": "Bartone/Vidmanova"
          },
          {
            "name": "Vukovic/Hageman"
          }
        ],
        "rates": [
          "1.141",
          "-",
          "5.13",
          "-",
          "-",
          "-",
          "-",
          "-",
          "-"
        ]
      }
    ],
    "head": [
      "1",
      "X",
      "2",
      "O",
      "TOTAL",
      "U",
      "1",
      "HANDICAP",
      "2"
    ]
  },
  {
    "Event": "ITF. Telfs. Doubles",
    "matches": [
      {
        "game1": [
          {
            "name": "Benson/Vasser"
          },
          {
            "name": "D'Agostino/Plunger"
          }
        ],
        "rates": [
          "3.175",
          "-",
          "1.32",
          "-",
          "-",
          "-",
          "-",
          "-",
          "-"
        ]
      }
    ],
    "head": [
      "1",
      "X",
      "2",
      "O",
      "TOTAL",
      "U",
      "1",
      "HANDICAP",
      "2"
    ]
  },
  {
    "Event": "ITF. Tianjin. Women. Doubles",
    "matches": [
      {
        "game1": [
          {
            "name": "Ayukawa/Kawamura"
          },
          {
            "name": "Huang/Zheng"
          }
        ],
        "rates": [
          "2.238",
          "-",
          "1.6",
          "-",
          "-",
          "-",
          "-",
          "-",
          "-"
        ]
      }
    ],
    "head": [
      "1",
      "X",
      "2",
      "O",
      "TOTAL",
      "U",
      "1",
      "HANDICAP",
      "2"
    ]
  },
  {
    "Event": "ITF. Vitoria-Gasteiz. Women",
    "matches": [
      {
        "game1": [
          {
            "name": "Victoria Jimenez Kasintseva"
          },
          {
            "name": "Jessika Ponchet"
          }
        ],
        "rates": [
          "1.92",
          "-",
          "1.8",
          "1.78",
          "20.5",
          "1.93",
          "1.86",
          "+0.5-",
          "1.85"
        ]
      }
    ],
    "head": [
      "1",
      "X",
      "2",
      "O",
      "TOTAL",
      "U",
      "1",
      "HANDICAP",
      "2"
    ]
  },
  {
    "Event": "WTA. Iasi. Qualification",
    "matches": [
      {
        "game1": [
          {
            "name": "Georgia Andreea Craciun"
          },
          {
            "name": "Marie Benoit"
          }
        ],
        "rates": [
          "4.4",
          "-",
          "1.193",
          "1.9",
          "19.5",
          "1.82",
          "1.86",
          "+5.5-",
          "1.86"
        ]
      },
      {
        "game2": [
          {
            "name": "Natalia Szabanin"
          },
          {
            "name": "Gergana Topalova"
          }
        ],
        "rates": [
          "3.655",
          "-",
          "1.26",
          "1.81",
          "19.5",
          "1.909",
          "1.7",
          "+5.5-",
          "2.05"
        ]
      },
      {
        "game3": [
          {
            "name": "Varvara Lepchenko"
          },
          {
            "name": "Ilinca Dalina Amariei"
          }
        ],
        "rates": [
          "1.08",
          "-",
          "7.13",
          "1.93",
          "18.5",
          "1.79",
          "1.92",
          "-6.5+",
          "1.81"
        ]
      }
    ],
    "head": [
      "1",
      "X",
      "2",
      "O",
      "TOTAL",
      "U",
      "1",
      "HANDICAP",
      "2"
    ]
  },
  {
    "Event": "WTA. Prague. Qualification",
    "matches": [
      {
        "game1": [
          {
            "name": "Eliska Tichackova"
          },
          {
            "name": "Kathinka Von Deichmann"
          }
        ],
        "rates": [
          "7.45",
          "-",
          "1.072",
          "1.96",
          "18.5",
          "1.77",
          "1.85",
          "+6.5-",
          "1.87"
        ]
      },
      {
        "game2": [
          {
            "name": "Eva Vedder"
          },
          {
            "name": "Tereza Martincova"
          }
        ],
        "rates": [
          "3.07",
          "-",
          "1.35",
          "1.92",
          "20.5",
          "1.8",
          "1.85",
          "+4.5-",
          "1.87"
        ]
      },
      {
        "game3": [
          {
            "name": "Ipek Oz"
          },
          {
            "name": "Alison Van Uytvanck"
          }
        ],
        "rates": [
          "2.925",
          "-",
          "1.38",
          "1.833",
          "20.5",
          "1.89",
          "1.76",
          "+4.5-",
          "1.97"
        ]
      },
      {
        "game4": [
          {
            "name": "Louisa Chirico"
          },
          {
            "name": "Camilla Rosatello"
          }
        ],
        "rates": [
          "1.4",
          "-",
          "2.837",
          "1.89",
          "20.5",
          "1.83",
          "1.99",
          "-4.5+",
          "1.75"
        ]
      },
      {
        "game5": [
          {
            "name": "Conny Perrin"
          },
          {
            "name": "Tereza Martincova"
          }
        ],
        "rates": [
          "2.837",
          "-",
          "1.35",
          "-",
          "-",
          "-",
          "-",
          "-",
          "-"
        ]
      }
    ],
    "head": [
      "1",
      "X",
      "2",
      "O",
      "TOTAL",
      "U",
      "1",
      "HANDICAP",
      "2"
    ]
  },
  {
    "Event": "ATP. Bastad. 2024. Winner",
    "matches": [],
    "head": [
      "RAFAEL NADAL",
      "DUJE AJDUKOVIC",
      "NUNO BORGES",
      "THIAGO AGUSTIN TIRANTE",
      "TO WIN - YES"
    ]
  },
  {
    "Event": "ATP. Hamburg. Doubles",
    "matches": [
      {
        "game1": [
          {
            "name": "Jebens/Frantzen"
          },
          {
            "name": "Krawietz/Puetz"
          }
        ],
        "rates": [
          "3.03",
          "-",
          "1.36",
          "-",
          "-",
          "-",
          "-",
          "-",
          "-"
        ]
      }
    ],
    "head": [
      "1",
      "X",
      "2",
      "O",
      "TOTAL",
      "U",
      "1",
      "HANDICAP",
      "2"
    ]
  },
  {
    "Event": "ITF. Darmstadt. Women",
    "matches": [
      {
        "game1": [
          {
            "name": "Victoria Mboko"
          },
          {
            "name": "Anouk Koevermans"
          }
        ],
        "rates": [
          "1.53",
          "-",
          "2.392",
          "1.83",
          "20.5",
          "1.88",
          "1.89",
          "-3.5+",
          "1.82"
        ]
      }
    ],
    "head": [
      "1",
      "X",
      "2",
      "O",
      "TOTAL",
      "U",
      "1",
      "HANDICAP",
      "2"
    ]
  },
  {
    "Event": "ITF. Esch-sur-Alzette. Doubles",
    "matches": [
      {
        "game1": [
          {
            "name": "Sobbe/Hartig"
          },
          {
            "name": "Calzi/Raynel"
          }
        ],
        "rates": [
          "3.31",
          "-",
          "1.3",
          "-",
          "-",
          "-",
          "-",
          "-",
          "-"
        ]
      }
    ],
    "head": [
      "1",
      "X",
      "2",
      "O",
      "TOTAL",
      "U",
      "1",
      "HANDICAP",
      "2"
    ]
  },
  {
    "Event": "ITF. Kursumlijska Banja. Doubles",
    "matches": [
      {
        "game1": [
          {
            "name": "Dinev/Latinovic"
          },
          {
            "name": "Barbier Gazeu/Pietri"
          }
        ],
        "rates": [
          "2.238",
          "-",
          "1.6",
          "-",
          "-",
          "-",
          "-",
          "-",
          "-"
        ]
      }
    ],
    "head": [
      "1",
      "X",
      "2",
      "O",
      "TOTAL",
      "U",
      "1",
      "HANDICAP",
      "2"
    ]
  },
  {
    "Event": "ITF. Nottingham",
    "matches": [
      {
        "game1": [
          {
            "name": "George Loffhagen"
          },
          {
            "name": "Lucas Poullain"
          }
        ],
        "rates": [
          "1.41",
          "-",
          "2.754",
          "1.79",
          "20.5",
          "1.92",
          "1.76",
          "-3.5+",
          "1.96"
        ]
      },
      {
        "game2": [
          {
            "name": "James McCabe"
          },
          {
            "name": "Max Basing"
          }
        ],
        "rates": [
          "1.4",
          "-",
          "2.794",
          "1.9",
          "21.5",
          "1.81",
          "1.78",
          "-3.5+",
          "1.94"
        ]
      }
    ],
    "head": [
      "1",
      "X",
      "2",
      "O",
      "TOTAL",
      "U",
      "1",
      "HANDICAP",
      "2"
    ]
  },
  {
    "Event": "ITF. Porto. Women",
    "matches": [
      {
        "game1": [
          {
            "name": "Lanlana Tararudee"
          },
          {
            "name": "Maja Chwalinska"
          }
        ],
        "rates": [
          "2.922",
          "-",
          "1.37",
          "1.9",
          "20.5",
          "1.81",
          "1.79",
          "+4.5-",
          "1.92"
        ]
      },
      {
        "game2": [
          {
            "name": "Gabriela Andrea Knutson"
          },
          {
            "name": "Tessah Andrianjafitrimo"
          }
        ],
        "rates": [
          "1.37",
          "-",
          "2.922",
          "1.9",
          "20.5",
          "1.81",
          "1.92",
          "-4.5+",
          "1.79"
        ]
      }
    ],
    "head": [
      "1",
      "X",
      "2",
      "O",
      "TOTAL",
      "U",
      "1",
      "HANDICAP",
      "2"
    ]
  },
  {
    "Event": "ITF. Slovenska Bistrica. Doubles",
    "matches": [
      {
        "game1": [
          {
            "name": "Bassem Sobhy/Zakaryia"
          },
          {
            "name": "Dominko/Kupcic"
          }
        ],
        "rates": [
          "2.922",
          "-",
          "1.37",
          "-",
          "-",
          "-",
          "-",
          "-",
          "-"
        ]
      }
    ],
    "head": [
      "1",
      "X",
      "2",
      "O",
      "TOTAL",
      "U",
      "1",
      "HANDICAP",
      "2"
    ]
  },
  {
    "Event": "ITF. Torino. Women",
    "matches": [
      {
        "game1": [
          {
            "name": "Guiomar Maristany Zuleta De Reales"
          },
          {
            "name": "Daria Lodikova"
          }
        ],
        "rates": [
          "1.373",
          "-",
          "2.912",
          "1.89",
          "20.5",
          "1.82",
          "1.94",
          "-4.5+",
          "1.78"
        ]
      }
    ],
    "head": [
      "1",
      "X",
      "2",
      "O",
      "TOTAL",
      "U",
      "1",
      "HANDICAP",
      "2"
    ]
  },
  {
    "Event": "ITF. Uslar",
    "matches": [
      {
        "game1": [
          {
            "name": "Mika Petkovic"
          },
          {
            "name": "Lautaro Agustin Falabella"
          }
        ],
        "rates": [
          "1.66",
          "-",
          "2.132",
          "1.909",
          "21.5",
          "1.8",
          "1.9",
          "-2.5+",
          "1.81"
        ]
      }
    ],
    "head": [
      "1",
      "X",
      "2",
      "O",
      "TOTAL",
      "U",
      "1",
      "HANDICAP",
      "2"
    ]
  },
  {
    "Event": "Polish National Championships. Women",
    "matches": [
      {
        "game1": [
          {
            "name": "Martyna Kubka"
          },
          {
            "name": "Veronika Ewald"
          }
        ],
        "rates": [
          "1.51",
          "-",
          "2.498",
          "-",
          "-",
          "-",
          "-",
          "-",
          "-"
        ]
      }
    ],
    "head": [
      "1",
      "X",
      "2",
      "O",
      "TOTAL",
      "U",
      "1",
      "HANDICAP",
      "2"
    ]
  },
  {
    "Event": "WTA. Budapest. 2024. Winner",
    "matches": [],
    "head": [
      "ALIAKSANDRA SASNOVICH",
      "EVA LYS",
      "DIANA SHNAIDER",
      "ANNA KAROLÍNA SCHMIEDLOVA",
      "TO WIN - YES"
    ]
  }
]